Metadata-Version: 2.1
Name: pytest-parametrization
Version: 2022.2.1
Summary: Simpler PyTest parametrization
Home-page: https://github.com/singular-labs/parametrization
Author: Singular Labs, Inc
Author-email: devs@singular.net
License: MIT License
Keywords: pytest,parametrize,parametrization,singular
Platform: UNKNOWN
Classifier: Development Status :: 5 - Production/Stable
Classifier: Intended Audience :: Developers
Classifier: Topic :: Software Development :: Build Tools
Classifier: License :: OSI Approved :: MIT License
Classifier: Programming Language :: Python :: 2.7
Classifier: Programming Language :: Python :: 3.4
Classifier: Programming Language :: Python :: 3.5
Classifier: Programming Language :: Python :: 3.6
Provides: parametrization
Requires-Python: >=2.6, !=3.0.*, !=3.1.*, !=3.2.*, !=3.3.*
